ldr/environment/__init__.py
ldr/environment/config.py
ldr/environment/errors.py
ldr/environment/google.py
ldr/environment/var.py
ldr_environment-0.1.0.dist-info/METADATA
ldr_environment-0.1.0.dist-info/WHEEL
ldr_environment-0.1.0.dist-info/RECORD
