Metadata-Version: 2.4
Name: ldr-environment
Version: 0.1.0
Summary: Methods to interact with the environment.
Author-email: Louder <devops@louder.com.au>
Requires-Python: >=3.12
Requires-Dist: pydantic-settings>=2.12.0
Requires-Dist: pydantic>=2.0
Requires-Dist: typing-extensions>=4.15.0
